animesub/__init__.py
animesub/asr_whisper.py
animesub/download_video.py
animesub/gui.py
animesub/main_logic.py
animesub/model_manager.py
animesub/punctuator.py
animesub/separator.py
animesub/srt_formatter.py
animesub/utils.py
animesub/vad_detector.py
animesub-1.0.3.dist-info/licenses/LICENSE
animesub-1.0.3.dist-info/METADATA
animesub-1.0.3.dist-info/WHEEL
animesub-1.0.3.dist-info/entry_points.txt
animesub-1.0.3.dist-info/top_level.txt
animesub-1.0.3.dist-info/RECORD
