Metadata-Version: 2.4
Name: animesub
Version: 1.0.3
Summary: Инструмент для автоматического создания субтитров для аниме
Author-email: Ivan Tyumentsev <ivanfufa184@gmail.com>
License: MIT
Project-URL: Homepage, https://github.com/iniquitousworld/animesub
Project-URL: Documentation, https://github.com/iniquitousworld/animesub#readme
Project-URL: Issues, https://github.com/iniquitousworld/animesub/issues
Classifier: Programming Language :: Python :: 3
Classifier: License :: OSI Approved :: MIT License
Classifier: Operating System :: OS Independent
Classifier: Topic :: Multimedia :: Video :: Conversion
Classifier: Topic :: Text Processing :: Linguistic
Requires-Python: >=3.8
License-File: LICENSE
Requires-Dist: torch>=2.2.0
Requires-Dist: torchaudio>=2.2.0
Requires-Dist: faster-whisper>=1.2.0
Requires-Dist: transformers>=4.51.3
Requires-Dist: demucs>=4.0.0
Requires-Dist: punctuators>=0.0.5
Requires-Dist: soundfile>=0.12.1
Requires-Dist: numpy>=1.26.4
Requires-Dist: pyyaml>=6.0.2
Requires-Dist: tqdm>=4.67.1
Requires-Dist: sentencepiece>=0.2.0
Requires-Dist: ffmpeg-python>=0.2.0
Requires-Dist: diffq>=0.2.4
Requires-Dist: yt-dlp>=2025.1.26
Dynamic: license-file
